nr7/Devil.so
nr7/__init__.py
nr7-1.0.0.dist-info/METADATA
nr7-1.0.0.dist-info/WHEEL
nr7-1.0.0.dist-info/top_level.txt
nr7-1.0.0.dist-info/RECORD
