Metadata-Version: 2.4
Name: NR7
Version: 1.0.0
Summary: NR7 package with native Devil core
Home-page: https://t.me/NexLangPy
Author: NexLangPy
Author-email: nasrpy99@gmail.com
Requires-Python: >=3.7
Dynamic: author
Dynamic: author-email
Dynamic: description
Dynamic: description-content-type
Dynamic: home-page
Dynamic: requires-python
Dynamic: summary
